pan_from_gstin/app.py
pan_from_gstin/logger_class.py
pan_from_gstin-0.2.dist-info/LICENSE.txt
pan_from_gstin-0.2.dist-info/METADATA
pan_from_gstin-0.2.dist-info/WHEEL
pan_from_gstin-0.2.dist-info/top_level.txt
pan_from_gstin-0.2.dist-info/RECORD
